dolze_image_templates/__init__.py
dolze_image_templates/exceptions.py
dolze_image_templates/resources.py
dolze_image_templates/available_templates/add_branding.json
dolze_image_templates/available_templates/announcement_template.json
dolze_image_templates/available_templates/business_highlights_2035_html.json
dolze_image_templates/available_templates/contact_us_overlay.json
dolze_image_templates/available_templates/customer_retention_strategies.json
dolze_image_templates/available_templates/faq_template.json
dolze_image_templates/available_templates/faq_white_post.json
dolze_image_templates/available_templates/food_offer_promo.json
dolze_image_templates/available_templates/hiring_minimal_red.json
dolze_image_templates/available_templates/hiring_post.json
dolze_image_templates/available_templates/marketing_trends_list.json
dolze_image_templates/available_templates/myth_or_fact.json
dolze_image_templates/available_templates/neon_creative_agency.json
dolze_image_templates/available_templates/perfect_job_search_template.json
dolze_image_templates/available_templates/process_steps.json
dolze_image_templates/available_templates/product_sale_2.json
dolze_image_templates/available_templates/product_showcase_3.json
dolze_image_templates/available_templates/product_showcase_4.json
dolze_image_templates/available_templates/search_services_listing.json
dolze_image_templates/available_templates/social_media.json
dolze_image_templates/available_templates/social_media_2.json
dolze_image_templates/available_templates/social_media_tips_template.json
dolze_image_templates/available_templates/spotlight_launching.json
dolze_image_templates/available_templates/spotlight_launching_text.json
dolze_image_templates/available_templates/stocks_dividend_post.json
dolze_image_templates/available_templates/testimonial_card.json
dolze_image_templates/available_templates/why_us_reasons.json
dolze_image_templates/components/__init__.py
dolze_image_templates/components/base.py
dolze_image_templates-1.2.9.dist-info/METADATA
dolze_image_templates-1.2.9.dist-info/WHEEL
dolze_image_templates-1.2.9.dist-info/top_level.txt
dolze_image_templates-1.2.9.dist-info/RECORD
