Metadata-Version: 2.4
Name: dolze-image-templates
Version: 1.2.9
Summary: A package for generating Dolze templates
Home-page: https://github.com/yourusername/dolze-templates
Author: Dolze Team
Author-email: Dolze team <dolze@team.com>
License: MIT
Classifier: Programming Language :: Python :: 3
Classifier: License :: OSI Approved :: MIT License
Classifier: Operating System :: OS Independent
Requires-Python: >=3.6
Requires-Dist: Pillow>=9.0.0
Requires-Dist: httpx>=0.24.0
Requires-Dist: typing_extensions>=4.12.2
Requires-Dist: cairosvg
Provides-Extra: html
Requires-Dist: playwright>=1.0.0; extra == "html"
Provides-Extra: all
Requires-Dist: Pillow>=9.0.0; extra == "all"
Requires-Dist: httpx>=0.24.0; extra == "all"
Requires-Dist: typing_extensions>=4.12.2; extra == "all"
Requires-Dist: cairosvg; extra == "all"
Requires-Dist: playwright>=1.0.0; extra == "all"
Dynamic: author
Dynamic: home-page
Dynamic: requires-python
